vector_datalib/__init__.py
vector_datalib/meta.py
vector_datalib/application/__init__.py
vector_datalib/application/main.py
vector_datalib/application/services/__init__.py
vector_datalib/application/services/cache_service.py
vector_datalib/application/services/coordinate_service.py
vector_datalib/domain/__init__.py
vector_datalib/domain/coordinates/__init__.py
vector_datalib/domain/coordinates/central_axis.py
vector_datalib/domain/coordinates/vector_point.py
vector_datalib/domain/mappings/__init__.py
vector_datalib/domain/mappings/coordinate_mapping.py
vector_datalib/domain/spaces/__init__.py
vector_datalib/domain/spaces/dimensional_space.py
vector_datalib/infrastructure/__init__.py
vector_datalib/infrastructure/storage/__init__.py
vector_datalib/infrastructure/storage/file_storage.py
vector_datalib-1.4.0b0.dist-info/licenses/LICENSE
vector_datalib-1.4.0b0.dist-info/METADATA
vector_datalib-1.4.0b0.dist-info/WHEEL
vector_datalib-1.4.0b0.dist-info/top_level.txt
vector_datalib-1.4.0b0.dist-info/RECORD
