Metadata-Version: 2.4
Name: vector-datalib
Version: 1.4.0b0
Summary: VECTOR: N-dimensional coordinate database with O(1) lookups
Author-email: Domas Leščinskas <domas.lescinskas@gmail.com>
License: Apache-2.0
Project-URL: Homepage, https://github.com/domasles/vector
Project-URL: Bug Reports, https://github.com/domasles/vector/issues
Project-URL: Source, https://github.com/domasles/vector
Project-URL: Documentation, https://github.com/domasles/vector#readme
Keywords: database,vector,coordinates,dimensions,lookup,fast
Classifier: Development Status :: 4 - Beta
Classifier: Intended Audience :: Developers
Classifier: Topic :: Database
Classifier: Topic :: Database :: Database Engines/Servers
Classifier: Topic :: Scientific/Engineering :: Mathematics
Classifier: License :: OSI Approved :: Apache Software License
Classifier: Programming Language :: Python :: 3.11
Classifier: Programming Language :: Python :: 3.12
Classifier: Programming Language :: Python :: 3.13
Classifier: Programming Language :: Python :: 3.14
Classifier: Operating System :: OS Independent
Requires-Python: >=3.11
License-File: LICENSE
Requires-Dist: msgpack>=1.0.0
Requires-Dist: aiofiles>=23.0.0
Provides-Extra: dev
Requires-Dist: pytest>=6.0; extra == "dev"
Requires-Dist: pytest-cov; extra == "dev"
Requires-Dist: black; extra == "dev"
Requires-Dist: pre-commit; extra == "dev"
Requires-Dist: flake8; extra == "dev"
Requires-Dist: mypy; extra == "dev"
Provides-Extra: test
Requires-Dist: pytest>=6.0; extra == "test"
Requires-Dist: pytest-cov; extra == "test"
Dynamic: license-file
